setup.py
question_stack.egg-info/PKG-INFO
question_stack.egg-info/SOURCES.txt
question_stack.egg-info/dependency_links.txt
question_stack.egg-info/top_level.txt
stack/__init__.py
stack/admin.py
stack/forms.py
stack/lookups.py
stack/models.py
stack/tests.py
stack/urls.py
stack/views.py
stack/migrations/0001_initial.py
stack/migrations/0002_auto__add_field_question_site.py
stack/migrations/__init__.py
stack/templatetags/__init__.py
stack/templatetags/stack_tags.py