Metadata-Version: 1.0
Name: question-stack
Version: 0.1
Summary: Managing stackoverflow-like-situations in Django
Home-page: http://github.com/subsume/question-stack
Author: Steve Yeago
Author-email: subsume@gmail.com
License: UNKNOWN
Platform: UNKNOWN
Classifier: Framework :: Django
Classifier: Intended Audience :: Developers
Classifier: Intended Audience :: System Administrators
Classifier: Operating System :: OS Independent
Classifier: Topic :: Software Development
